pygments_apiblueprint/__init__.py
pygments_apiblueprint/lexer.py
pygments_apiblueprint-0.2.0.dist-info/LICENSE
pygments_apiblueprint-0.2.0.dist-info/METADATA
pygments_apiblueprint-0.2.0.dist-info/WHEEL
pygments_apiblueprint-0.2.0.dist-info/entry_points.txt
pygments_apiblueprint-0.2.0.dist-info/top_level.txt
pygments_apiblueprint-0.2.0.dist-info/RECORD
