Metadata-Version: 2.1
Name: pygments-apiblueprint
Version: 0.2.0
Summary: An API Blueprint Lexer for Pygments.
Home-page: https://github.com/kylef/pygments-apiblueprint
Author: Kyle Fuller
Author-email: kyle@fuller.li
License: BSD
Platform: UNKNOWN
Classifier: Development Status :: 5 - Production/Stable
Classifier: Programming Language :: Python :: 3.5
Classifier: Programming Language :: Python :: 3.6
Classifier: License :: OSI Approved :: BSD License
Requires-Dist: Pygments
